sandro/__init__.py
sandro-1.0.0.dist-info/WHEEL
sandro-1.0.0.dist-info/METADATA
sandro-1.0.0.dist-info/RECORD
